{
   "type": "list",
   "headline": "СОНИК В КИНО",
   "preload": "next",
   "overlay": {
      "items": [
         {
            "type": "space",
            "layout": "6,0,6,6",
            "offset": "0.58,-1,0.17,1.67",
            "color": "msx-black-soft"
         },
         {
            "id": "image",
            "type": "space",
            "layout": "7,0,5,3",
            "color": "msx-glass",
            "image": "none",
            "imageFiller": "cover"
         },
         {
            "id": "text",
            "type": "space",
            "layout": "7,3,5,3",
            "headline": "",
            "text": ""
         }
      ]
   },
   "template": {
      "type": "default",
      "layout": "0,0,6,1",
      "area": "0,0,6,6",
      "wrapperColor": "msx-glass",
      "imageWidth": 1.83,
      "color": "msx-glass",
      "imageFiller": "cover"
   },
   "items": [
      {
         "titleHeader": "{col:msx-white}Соник в кино",
         "titleFooter": "Соник в кино",
         "selection": {
            "important": true,
            "action": "[update:content:overlay:image|update:content:overlay:text]",
            "data": {
               "text": "{col:msx-white}Соник в кино{col}{br}Отвязный ярко-синий ёжик Соник из параллельного мира вместе с новообретённым лучшим другом-человеком по имени Том знакомится со сложностями жизни на Земле и противостоит злодейскому доктору Роботнику, который хочет пленить ёжика и использовать его безграничные суперсилы для завоевания мирового господства.",
               "image": "https://flxt.tmsimg.com/assets/p15835896_k_h9_ab.jpg"
            }
         },
         "image": "https://flxt.tmsimg.com/assets/p15835896_k_h9_ab.jpg",
         "action": "video:resolve:request:interaction:https://hye1eaipby4w.takedwn.ws/05_14_21/05/14/17/SWLRRE7S/5UDM6DGB.mp4/master.m3u8@http://msx.benzac.de/interaction/play.html",
         "properties": {
            "image:extension": "| {col:msx-white}First Item"
         }
      },
      {
         "titleHeader": "{col:msx-white}Соник в кино",
         "titleFooter": "Соник 2 в кино",
         "selection": {
            "important": true,
            "action": "[update:content:overlay:image|update:content:overlay:text]",
            "data": {
               "text": "{col:msx-white}Соник 2 в кино{col}{br}Поселившись в Грин-Хилз, Соник стремится доказать, что у него есть все задатки настоящего героя. И геройское испытание не заставляет себя долго ждать: злодейский доктор Роботник вновь строит козни. На этот раз — с загадочным напарником Наклзом. Вместе они разыскивают бесценный изумруд, в котором заключены силы, способные уничтожать целые цивилизации. Соник объединяется с лисенком Тейлзом, чтобы отправиться в кругосветное путешествие и найти изумруд до того, как он попадет в плохие руки.",
               "image": "https://i.ytimg.com/vi/APgJgH1cdpI/maxresdefault.jpg"
            }
         },
         "image": "https://i.ytimg.com/vi/APgJgH1cdpI/maxresdefault.jpg",
         "action": "video:resolve:request:interaction:https://hye1eaipby4w.takedwn.ws/09_28_22/09/28/23/USC2VEI5/5SDUUOHN.mp4/master.m3u8@http://msx.benzac.de/interaction/play.html",
         "properties": {
            "image:extension": "| {col:msx-white}Second Item"
         }
      }
   ]
}
