{
   "type": "list",
   "headline": "Иван Царевич и Серый Волк ",
   "preload": "next",
   "overlay": {
      "items": [
         {
            "type": "space",
            "layout": "6,0,6,6",
            "offset": "0.58,-1,0.17,1.67",
            "color": "msx-black-soft"
         },
         {
            "id": "image",
            "type": "space",
            "layout": "7,0,5,3",
            "color": "msx-glass",
            "image": "none",
            "imageFiller": "cover"
         },
         {
            "id": "text",
            "type": "space",
            "layout": "7,3,5,3",
            "headline": "",
            "text": ""
         }
      ]
   },
   "template": {
      "type": "default",
      "layout": "0,0,6,1",
      "area": "0,0,6,6",
      "wrapperColor": "msx-glass",
      "imageWidth": 1.83,
      "color": "msx-glass",
      "imageFiller": "cover"
   },
   "items": [
      {
         "titleHeader": "{col:msx-white}Иван Царевич и Серый Волк ",
         "titleFooter": "Иван Царевич и Серый Волк ",
         "selection": {
            "important": true,
            "action": "[update:content:overlay:image|update:content:overlay:text]",
            "data": {
               "text": "{col:msx-white}Иван Царевич и Серый Волк (2011){col}{br}В некотором царстве, в некотором государстве жила-была Василиса, царская дочь. Умная, красивая, но с характером: замуж - только по любви. Старенький царь уже отчаялся искать женихов и обещает выдать царевну за первого встречного.",
               "image": "https://i.ytimg.com/vi/SCq2l7K4QDM/maxresdefault.jpg?sqp=-oaymwEmCIAKENAF8quKqQMa8AEB-AH-CYAC0AWKAgwIABABGGUgXihMMA8=&amp;rs=AOn4CLD3NdxNiTcTtW1s6lyFVb40Y7AICQ"
            }
         },
         "image": "https://i.ytimg.com/vi/SCq2l7K4QDM/maxresdefault.jpg?sqp=-oaymwEmCIAKENAF8quKqQMa8AEB-AH-CYAC0AWKAgwIABABGGUgXihMMA8=&amp;rs=AOn4CLD3NdxNiTcTtW1s6lyFVb40Y7AICQ",
         "action": "video:resolve:request:interaction:https://hye1eaipby4w.takedwn.ws/10_15_20/10/15/22/OWVUQDZU/CKO6VEEA.mp4/master.m3u8@http://msx.benzac.de/interaction/play.html",
         "properties": {
            "image:extension": "| {col:msx-white}First Item"
         }
      },
      {
         "titleHeader": "{col:msx-white}Иван Царевич и Серый Волк",
         "titleFooter": "Иван Царевич и Серый Волк 2",
         "selection": {
            "important": true,
            "action": "[update:content:overlay:image|update:content:overlay:text]",
            "data": {
               "text": "{col:msx-white}Иван Царевич и Серый Волк 2 (2013){col}{br}Любит Иван свою Василису, да не до конца понимает, что так жить нельзя! Ивана да Серого волка хлебом не корми, дай только службу вести достойно, хоть домой не приходи! А ведь Василисе, с которой он сыграл свадьбу, скучно самой дома, когда любимого нету и нету. И придумывает она приключение, да чтоб такое, как в прошлый раз!",
               "image": "https://pic.uma.media/pic/cardimage/66/52/6652da85cef05ebd04d968d73db71efa.jpg?size=1603&quality=80"
            }
         },
         "image": "https://pic.uma.media/pic/cardimage/66/52/6652da85cef05ebd04d968d73db71efa.jpg?size=1603&quality=80",
         "action": "video:resolve:request:interaction:https://hye1eaipby4w.takedwn.ws/09_05_18/09/05/10/8ZElFUw6/1080_edr2L9OD.mp4/master.m3u8@http://msx.benzac.de/interaction/play.html",
         "properties": {
            "image:extension": "| {col:msx-white}Second Item"
         }
      },
      {
         "titleHeader": "{col:msx-white}Иван Царевич и Серый Волк",
         "titleFooter": "Иван Царевич и Серый Волк 3",
         "selection": {
            "important": true,
            "action": "[update:content:overlay:image|update:content:overlay:text]",
            "data": {
               "text": "{col:msx-white}Иван Царевич и Серый Волк 3 (2015){col}{br}Царь собирает пожитки, берет в руки удочку и отправляется на деревенское лоно. Вместо царя на страже порядка в государстве остались Иван Царевич и Серый Волк. У Ивана дел невпроворот, а тут еще жена Василиса обижается на мужа за то, что он не устроил ей свадебного путешествия.",
               "image": "https://i.ytimg.com/vi/VPqNgYck8Pk/maxresdefault.jpg"
            }
         },
         "image": "https://i.ytimg.com/vi/VPqNgYck8Pk/maxresdefault.jpg",
         "action": "video:resolve:request:interaction:https://hye1eaipby4w.takedwn.ws/01_21_21/01/21/17/GFMSTZW3/F3XNU6MJ.mp4/master.m3u8@http://msx.benzac.de/interaction/play.html",
         "properties": {
            "image:extension": "| {col:msx-white}First Item"
         }
      },
      {
         "titleHeader": "{col:msx-white}Иван Царевич и Серый Волк",
         "titleFooter": "Иван Царевич и Серый Волк 4",
         "selection": {
            "important": true,
            "action": "[update:content:overlay:image|update:content:overlay:text]",
            "data": {
               "text": "{col:msx-white}Иван Царевич и Серый Волк 4 (2019){col}{br}Накануне весны главные герои узнают, что в Трисемнадцатом царстве пройдёт глобальный песенный конкурс. Царь объявил, что от Тридевятого царства будет выступать Кот-учёный. Иван Царевич и его друзья попытаются ему помочь, но они даже не представляют, насколько опасными окажутся их соперники.",
               "image": "https://i.ytimg.com/vi/gtTPHqB4dHc/hq720.jpg?sqp=-oaymwEhCK4FEIIDSFryq4qpAxMIARUAAAAAGAElAADIQj0AgKJD&rs=AOn4CLBEOzyHOUVkheOSKYxl-po5fI66sg"
            }
         },
         "image": "https://i.ytimg.com/vi/gtTPHqB4dHc/hq720.jpg?sqp=-oaymwEhCK4FEIIDSFryq4qpAxMIARUAAAAAGAElAADIQj0AgKJD&rs=AOn4CLBEOzyHOUVkheOSKYxl-po5fI66sg",
         "action": "video:resolve:request:interaction:https://hye1eaipby4w.takedwn.ws/10_02_20/10/02/13/FRI4G7VR/VYYGBWDM.mp4/master.m3u8@http://msx.benzac.de/interaction/play.html",
         "properties": {
            "image:extension": "| {col:msx-white}Second Item"
         }
      },
      {
         "titleHeader": "{col:msx-white}Иван Царевич и Серый Волк",
         "titleFooter": "Иван Царевич и Серый Волк 5",
         "selection": {
            "important": true,
            "action": "[update:content:overlay:image|update:content:overlay:text]",
            "data": {
               "text": "{col:msx-white}Иван Царевич и Серый Волк 5 (2022){col}{br}После беспечного путешествия в прошлое все, включая Василису, забыли, кто такой Иван. Теперь ему с Серым волком нужно снова добиваться принцессы.",
               "image": "https://kinofilm.ca/uploads/promo/3337407532.jpeg"
            }
         },
         "image": "https://kinofilm.ca/uploads/promo/3337407532.jpeg",
         "action": "video:resolve:request:interaction:https://hye1eaipby4w.takedwn.ws/02_28_23/02/28/11/GU7KRTMR/5YTAXIMB.mp4/master.m3u8@http://msx.benzac.de/interaction/play.html",
         "properties": {
            "image:extension": "| {col:msx-white}First Item"
         }
      }
   ]
}